[{"ecran":"ECRAN SAMSUNG 18,5&quot; LED ","marque":"SAMSUNG","lien":"http:\/\/www.mytek.tn\/ecran-tunisie\/5209-ecran-samsung-185-led-tunsie.html","photo":"http:\/\/www.mytek.tn\/28311-product_category\/ecran-samsung-185-led-tunsie.jpg","prix":" 196,000 DT "},{"ecran":"Ecran SAMSUNG 20&quot; LED ","marque":"SAMSUNG","lien":"http:\/\/www.mytek.tn\/ecran-tunisie\/1905-ecran-samsung-20-led-tunsie.html","photo":"http:\/\/www.mytek.tn\/21311-product_category\/ecran-samsung-20-led-tunsie.jpg","prix":" 209,000 DT "},{"ecran":"\u00c9cran Asus VX207DE 19.5&quot; HD LED","marque":"Asus","lien":"http:\/\/www.mytek.tn\/ecran-tunisie\/6114-ecran-asus-vx207de-195-hd-led-tunsie.html","photo":"http:\/\/www.mytek.tn\/31803-product_category\/ecran-asus-vx207de-195-hd-led-tunsie.jpg","prix":" 219,000 DT "},{"ecran":"Ecran DELL 20&quot; LED","marque":"DELL","lien":"http:\/\/www.mytek.tn\/ecran-tunisie\/197-ecran-dell-20-led-tunsie.html","photo":"http:\/\/www.mytek.tn\/524-product_category\/ecran-dell-20-led-tunsie.jpg","prix":" 219,000 DT "},{"ecran":"Ecran 20&quot; HP","marque":"20&quot;","lien":"http:\/\/www.mytek.tn\/ecran-tunisie\/4352-ecran-20-hp-tunsie.html","photo":"http:\/\/www.mytek.tn\/28318-product_category\/ecran-20-hp-tunsie.jpg","prix":" 249,000 DT "},{"ecran":" Ecran HP W2072a LCD 20&quot; ","marque":"Ecran","lien":"http:\/\/www.mytek.tn\/ecran-tunisie\/5059-ecran-hp-w2072a-lcd-20-tunsie.html","photo":"http:\/\/www.mytek.tn\/28319-product_category\/ecran-hp-w2072a-lcd-20-tunsie.jpg","prix":" 269,000 DT "},{"ecran":"\u00c9cran Asus VS228DE 21.5&quot; HD LED","marque":"Asus","lien":"http:\/\/www.mytek.tn\/ecran-tunisie\/6115-ecran-asus-vs228de-215-hd-led-tunsie.html","photo":"http:\/\/www.mytek.tn\/31807-product_category\/ecran-asus-vs228de-215-hd-led-tunsie.jpg","prix":" 269,000 DT "},{"ecran":"\u00c9cran HP V201a 19,45&quot;","marque":"HP","lien":"http:\/\/www.mytek.tn\/ecran-tunisie\/4949-ecran-hp-v201a-1945-tunsie.html","photo":"http:\/\/www.mytek.tn\/28068-product_category\/ecran-hp-v201a-1945-tunsie.jpg","prix":" 269,000 DT "},{"ecran":"Ecran HP ProDisplay P201 20&quot; ","marque":"HP","lien":"http:\/\/www.mytek.tn\/ecran-tunisie\/4950-ecran-hp-prodisplay-p201-20-tunsie.html","photo":"http:\/\/www.mytek.tn\/28071-product_category\/ecran-hp-prodisplay-p201-20-tunsie.jpg","prix":" 299,000 DT "},{"ecran":"ECRAN SAMSUNG LED 22&quot; ","marque":"SAMSUNG","lien":"http:\/\/www.mytek.tn\/ecran-tunisie\/5040-ecran-samsung-led-22-tunsie.html","photo":"http:\/\/www.mytek.tn\/28326-product_category\/ecran-samsung-led-22-tunsie.jpg","prix":" 309,000 DT "},{"ecran":"ECRAN SAMSUNG LED 24&quot; ","marque":"SAMSUNG","lien":"http:\/\/www.mytek.tn\/ecran-tunisie\/5038-ecran-samsung-led-24-tunsie.html","photo":"http:\/\/www.mytek.tn\/28328-product_category\/ecran-samsung-led-24-tunsie.jpg","prix":" 349,000 DT "},{"ecran":"ECRAN HP Pavilion 24cw ","marque":"HP","lien":"http:\/\/www.mytek.tn\/ecran-tunisie\/6413-ecran-hp-pavilion-24cw-tunsie.html","photo":"http:\/\/www.mytek.tn\/32872-product_category\/ecran-hp-pavilion-24cw-tunsie.jpg","prix":" 599,000 DT "},{"ecran":"ECRAN SAMSUNG 27&quot; LED","marque":"SAMSUNG","lien":"http:\/\/www.mytek.tn\/ecran-tunisie\/1909-ecran-samsung-27-led-tunsie.html","photo":"http:\/\/www.mytek.tn\/22163-product_category\/ecran-samsung-27-led-tunsie.jpg","prix":" 615,000 DT "},{"ecran":"ECRAN SAMSUNG 27&quot; LED CURVED","marque":"SAMSUNG","lien":"http:\/\/www.mytek.tn\/ecran-tunisie\/4539-ecran-samsung-27-led-curved-tunsie.html","photo":"http:\/\/www.mytek.tn\/28434-product_category\/ecran-samsung-27-led-curved-tunsie.jpg","prix":" 719,000 DT "},{"ecran":"\u00c9cran HP EliteDisplay E271i 27&quot;","marque":"HP","lien":"http:\/\/www.mytek.tn\/ecran-tunisie\/4956-ecran-hp-elitedisplay-e271i-27-tunsie.html","photo":"http:\/\/www.mytek.tn\/28399-product_category\/ecran-hp-elitedisplay-e271i-27-tunsie.jpg","prix":" 849,000 DT "}]