[{"tv":"TELEVISEUR TELEFUNKEN 4600B 24 &quot;LED HD","lien":"http:\/\/www.mytek.tn\/tv-led-tunisie\/6321-televiseur-telefunken-4600b-24-led-hd-tunsie.html","photo":"http:\/\/www.mytek.tn\/32567-product_category\/televiseur-telefunken-4600b-24-led-hd-tunsie.jpg","prix":" 399,000 DT ","marque":"TELEFUNKEN 4600B 24 &quot;LED HD","source":"Mytek"},{"tv":"TELEVISEUR SABA LED 32&quot; ","lien":"http:\/\/www.mytek.tn\/tv-led-tunisie\/2015-televiseur-saba-led-32-tunsie.html","photo":"http:\/\/www.mytek.tn\/22258-product_category\/televiseur-saba-led-32-tunsie.jpg","prix":" 465,000 DT ","marque":"SABA LED 32&quot; ","source":"Mytek"},{"tv":"TV TELEFUNKEN LED 32&quot; TKF E3000 HD TNT","lien":"http:\/\/www.mytek.tn\/tv-led-tunisie\/1405-tv-telefunken-led-32-tkf-e3000-hd-tnt-tunsie.html","photo":"http:\/\/www.mytek.tn\/24127-product_category\/tv-telefunken-led-32-tkf-e3000-hd-tnt-tunsie.jpg","prix":" 589,000 DT ","marque":" TELEFUNKEN LED 32&quot; TKF E3000 HD TNT","source":"Mytek"},{"tv":"TV TELEFUNKEN LED 32&quot; TLF226 Blanc","lien":"http:\/\/www.mytek.tn\/tv-led-tunisie\/1404-tv-telefunken-led-32-tlf226-blanc-tunsie.html","photo":"http:\/\/www.mytek.tn\/28379-product_category\/tv-telefunken-led-32-tlf226-blanc-tunsie.jpg","prix":" 589,000 DT ","marque":" TELEFUNKEN LED 32&quot; TLF226 Blanc","source":"Mytek"},{"tv":"TV SAMSUNG LED 32&quot; H4000","lien":"http:\/\/www.mytek.tn\/tv-led-tunisie\/2385-tv-samsung-led-32-h4000-tunsie.html","photo":"http:\/\/www.mytek.tn\/22238-product_category\/tv-samsung-led-32-h4000-tunsie.jpg","prix":" 685,000 DT ","marque":" SAMSUNG LED 32&quot; H4000","source":"Mytek"},{"tv":"T\u00e9l\u00e9vision LG 32","lien":"http:\/\/www.mytek.tn\/tv-led-tunisie\/3337-television-lg-32-tunsie.html","photo":"http:\/\/www.mytek.tn\/21372-product_category\/television-lg-32-tunsie.jpg","prix":" 699,000 DT ","marque":" LG 32","source":"Mytek"},{"tv":"TV SAMSUNG LED 32&quot; FH4003","lien":"http:\/\/www.mytek.tn\/tv-led-tunisie\/3488-tv-samsung-led-32-fh4003-tunsie.html","photo":"http:\/\/www.mytek.tn\/22222-product_category\/tv-samsung-led-32-fh4003-tunsie.jpg","prix":" 699,000 DT ","marque":" SAMSUNG LED 32&quot; FH4003","source":"Mytek"},{"tv":"TV SONY BRAVIA LED 32&quot;","lien":"http:\/\/www.mytek.tn\/tv-led-tunisie\/2118-tv-sony-bravia-led-32-tunsie.html","photo":"http:\/\/www.mytek.tn\/18918-product_category\/tv-sony-bravia-led-32-tunsie.jpg","prix":" 699,000 DT ","marque":" SONY BRAVIA LED 32&quot;","source":"Mytek"},{"tv":"TELEVISEUR SABA LED 40&quot; FULL HD","lien":"http:\/\/www.mytek.tn\/tv-led-tunisie\/2016-televiseur-saba-led-40-full-hd-tunsie.html","photo":"http:\/\/www.mytek.tn\/18933-product_category\/televiseur-saba-led-40-full-hd-tunsie.jpg","prix":" 749,000 DT ","marque":"SABA LED 40&quot; FULL HD","source":"Mytek"},{"tv":"TELEVISION SAMSUNG 32&#039;&#039; LED SLIM J4100 + Lecteur DVD E360","lien":"http:\/\/www.mytek.tn\/tv-led-tunisie\/5717-television-samsung-32-led-slim-j4100-lecteur-dvd-e360-tunsie.html","photo":"http:\/\/www.mytek.tn\/31111-product_category\/television-samsung-32-led-slim-j4100-lecteur-dvd-e360-tunsie.jpg","prix":" 759,000 DT ","marque":"TELEVISION SAMSUNG 32&#039;&#039; LED SLIM J4100 + Lecteur DVD E360","source":"Mytek"},{"tv":"TV TELEFUNKEN LED 40&quot; HD ","lien":"http:\/\/www.mytek.tn\/tv-led-tunisie\/5582-tv-telefunken-led-40-hd-tunsie.html","photo":"http:\/\/www.mytek.tn\/30390-product_category\/tv-telefunken-led-40-hd-tunsie.jpg","prix":" 819,000 DT ","marque":" TELEFUNKEN LED 40&quot; HD ","source":"Mytek"},{"tv":"TELEVISEUR SABA LED 42&quot; FULL HD","lien":"http:\/\/www.mytek.tn\/tv-led-tunisie\/4511-televiseur-saba-led-42-full-hd-tunsie.html","photo":"http:\/\/www.mytek.tn\/28385-product_category\/televiseur-saba-led-42-full-hd-tunsie.jpg","prix":" 829,000 DT ","marque":"SABA LED 42&quot; FULL HD","source":"Mytek"},{"tv":"TELEVISEUR SABA LED 48&quot;","lien":"http:\/\/www.mytek.tn\/tv-led-tunisie\/2688-televiseur-saba-led-48-tunsie.html","photo":"http:\/\/www.mytek.tn\/33028-product_category\/televiseur-saba-led-48-tunsie.jpg","prix":" 1 099,000 DT ","marque":"SABA LED 48&quot;","source":"Mytek"},{"tv":"TV TELEFUNKEN LED 42&quot; FULL HD SMART + R\u00c9CEPTEUR INT\u00c9GR\u00c9","lien":"http:\/\/www.mytek.tn\/tv-led-tunisie\/3120-tv-telefunken-led-42-full-hd-smart-recepteur-integre-tunsie.html","photo":"http:\/\/www.mytek.tn\/24129-product_category\/tv-telefunken-led-42-full-hd-smart-recepteur-integre-tunsie.jpg","prix":" 999,000 DT ","marque":" TELEFUNKEN LED 42&quot; FULL HD SMART + R\u00c9CEPTEUR INT\u00c9GR\u00c9","source":"Mytek"},{"tv":"Samsung H5000 40&quot; Full hd","lien":"http:\/\/www.mytek.tn\/tv-led-tunisie\/3129-samsung-h5000-40-full-hd-tunsie.html","photo":"http:\/\/www.mytek.tn\/19326-product_category\/samsung-h5000-40-full-hd-tunsie.jpg","prix":" 1 159,000 DT ","marque":"Samsung H5000 40&quot; Full hd","source":"Mytek"},{"tv":"TELEVISION SAMSUNG 40&#039;&#039; LED SLIM FHD J5100","lien":"http:\/\/www.mytek.tn\/tv-led-tunisie\/5236-television-samsung-40-led-slim-fhd-j5100-tunsie.html","photo":"http:\/\/www.mytek.tn\/28380-product_category\/television-samsung-40-led-slim-fhd-j5100-tunsie.jpg","prix":" 1 169,000 DT ","marque":"TELEVISION SAMSUNG 40&#039;&#039; LED SLIM FHD J5100","source":"Mytek"},{"tv":"TELEVISEUR TELEFUNKEN LED 48&quot; FULL HD","lien":"http:\/\/www.mytek.tn\/tv-led-tunisie\/5688-televiseur-telefunken-led-48-full-hd-tunsie.html","photo":"http:\/\/www.mytek.tn\/30701-product_category\/televiseur-telefunken-led-48-full-hd-tunsie.jpg","prix":" 1 199,000 DT ","marque":"TELEFUNKEN LED 48&quot; FULL HD","source":"Mytek"},{"tv":"Televiseur LG 43&quot; LED FULL HD 43LF5100","lien":"http:\/\/www.mytek.tn\/tv-led-tunisie\/5787-televiseur-lg-43-led-full-hd-43lf5100-tunsie.html","photo":"http:\/\/www.mytek.tn\/30925-product_category\/televiseur-lg-43-led-full-hd-43lf5100-tunsie.jpg","prix":" 1 219,000 DT ","marque":"Televiseur LG 43&quot; LED FULL HD 43LF5100","source":"Mytek"},{"tv":"TELEVISION SAMSUNG J5200 Smart 40&#039;&#039; Full HD","lien":"http:\/\/www.mytek.tn\/tv-led-tunisie\/6501-television-samsung-j5200-smart-40-full-hd.html","photo":"http:\/\/www.mytek.tn\/33181-product_category\/television-samsung-j5200-smart-40-full-hd.jpg","prix":" 1 249,000 DT ","marque":"TELEVISION SAMSUNG J5200 Smart 40&#039;&#039; Full HD","source":"Mytek"},{"tv":"TELEFUNKEN SMART 42&quot; Dual View + 3D + WIFI +R\u00e9cepteur Int\u00e9gr\u00e9 ","lien":"http:\/\/www.mytek.tn\/tv-led-tunisie\/3979-telefunken-smart-42-dual-view-3d-wifi-recepteur-integre-tunsie.html","photo":"http:\/\/www.mytek.tn\/24140-product_category\/telefunken-smart-42-dual-view-3d-wifi-recepteur-integre-tunsie.jpg","prix":" 1 299,000 DT ","marque":"TELEFUNKEN SMART 42&quot; Dual View + 3D + WIFI +R\u00e9cepteur Int\u00e9gr\u00e9 ","source":"Mytek"},{"tv":"TELEVISEUR TELEFUNKEN LED 48&quot; FULL HD","lien":"http:\/\/www.mytek.tn\/tv-led-tunisie\/6323-televiseur-telefunken-led-48-full-hd-tunsie.html","photo":"http:\/\/www.mytek.tn\/32571-product_category\/televiseur-telefunken-led-48-full-hd-tunsie.jpg","prix":" 1 399,000 DT ","marque":"TELEFUNKEN LED 48&quot; FULL HD","source":"Mytek"},{"tv":"TV TELEFUNKEN LED 50&quot; FULL HD SMART + R\u00c9CEPTEUR INT\u00c9GR\u00c9","lien":"http:\/\/www.mytek.tn\/tv-led-tunisie\/5502-tv-telefunken-led-50-full-hd-smart-recepteur-integre-tunsie.html","photo":"http:\/\/www.mytek.tn\/30128-product_category\/tv-telefunken-led-50-full-hd-smart-recepteur-integre-tunsie.jpg","prix":" 1 399,000 DT ","marque":" TELEFUNKEN LED 50&quot; FULL HD SMART + R\u00c9CEPTEUR INT\u00c9GR\u00c9","source":"Mytek"},{"tv":"Televiseur LG 49&quot; LED FULL HD 49LF5400","lien":"http:\/\/www.mytek.tn\/tv-led-tunisie\/5786-televiseur-lg-49-led-full-hd-49lf5400-tunsie.html","photo":"http:\/\/www.mytek.tn\/30922-product_category\/televiseur-lg-49-led-full-hd-49lf5400-tunsie.jpg","prix":" 1 539,000 DT ","marque":"Televiseur LG 49&quot; LED FULL HD 49LF5400","source":"Mytek"},{"tv":"TELEVISEUR SABA LED 55&quot; SMART FULL HD","lien":"http:\/\/www.mytek.tn\/tv-led-tunisie\/5684-televiseur-saba-led-55-smart-full-hd-tunsie.html","photo":"http:\/\/www.mytek.tn\/30687-product_category\/televiseur-saba-led-55-smart-full-hd-tunsie.jpg","prix":" 1 559,000 DT ","marque":"SABA LED 55&quot; SMART FULL HD","source":"Mytek"},{"tv":"TELEVISION SAMSUNG 48&#039;&#039; LED SLIM FHD CURVED SMART J6300","lien":"http:\/\/www.mytek.tn\/tv-led-tunisie\/5244-television-samsung-48-led-slim-fhd-curved-smart-j6300-tunsie.html","photo":"http:\/\/www.mytek.tn\/28391-product_category\/television-samsung-48-led-slim-fhd-curved-smart-j6300-tunsie.jpg","prix":" 2 399,000 DT ","marque":"TELEVISION SAMSUNG 48&#039;&#039; LED SLIM FHD CURVED SMART J6300","source":"Mytek"},{"tv":"TELEFUNKEN TV 55&quot; Dual View + 3D + UHD ","lien":"http:\/\/www.mytek.tn\/tv-led-tunisie\/1386-telefunken-tv-55-dual-view-3d-uhd-tunsie.html","photo":"http:\/\/www.mytek.tn\/24013-product_category\/telefunken-tv-55-dual-view-3d-uhd-tunsie.jpg","prix":" 2 690,000 DT ","marque":"TELEFUNKEN  55&quot; Dual View + 3D + UHD ","source":"Mytek"},{"tv":" Television Telefunken 65&quot; Full Hd 3D Smart Tv Wifi +Recepteur","lien":"http:\/\/www.mytek.tn\/tv-led-tunisie\/1408-television-telefunken-65-full-hd-3d-smart-tv-wifi-recepteur-tunsie.html","photo":"http:\/\/www.mytek.tn\/22086-product_category\/television-telefunken-65-full-hd-3d-smart-tv-wifi-recepteur-tunsie.jpg","prix":" 3 349,000 DT ","marque":" Television Telefunken 65&quot; Full Hd 3D Smart Tv Wifi +Recepteur","source":"Mytek"},{"tv":"TELEVISION SAMSUNG 55&#039;&#039; LED UHD Smart","lien":"http:\/\/www.mytek.tn\/tv-led-tunisie\/5487-television-samsung-55-led-uhd-smart-tunsie.html","photo":"http:\/\/www.mytek.tn\/29853-product_category\/television-samsung-55-led-uhd-smart-tunsie.jpg","prix":" 4 219,000 DT ","marque":"TELEVISION SAMSUNG 55&#039;&#039; LED UHD Smart","source":"Mytek"},{"tv":"TELEVISION SAMSUNG Smart 55&#039;&#039; Curved UHD 4K","lien":"http:\/\/www.mytek.tn\/tv-led-tunisie\/5891-television-samsung-smart-55-curved-uhd-4k-tunsie.html","photo":"http:\/\/www.mytek.tn\/31200-product_category\/television-samsung-smart-55-curved-uhd-4k-tunsie.jpg","prix":" 4 859,000 DT ","marque":"TELEVISION SAMSUNG Smart 55&#039;&#039; Curved UHD 4K","source":"Mytek"},{"tv":"TV SAMSUNG SMART LED Curved 65&quot;","lien":"http:\/\/www.mytek.tn\/tv-led-tunisie\/2006-tv-samsung-smart-led-curved-65-tunsie.html","photo":"http:\/\/www.mytek.tn\/19027-product_category\/tv-samsung-smart-led-curved-65-tunsie.jpg","prix":" 8 499,000 DT ","marque":" SAMSUNG SMART LED Curved 65&quot;","source":"Mytek"},{"tv":"TELEVISION SAMSUNG Smart 65&#039;&#039; SUHD JS9000 3D Curved 4K","lien":"http:\/\/www.mytek.tn\/tv-led-tunisie\/6424-television-samsung-smart-65-suhd-js9000-3d-curved-4k-tunsie.html","photo":"http:\/\/www.mytek.tn\/32935-product_category\/television-samsung-smart-65-suhd-js9000-3d-curved-4k-tunsie.jpg","prix":" 10 699,000 DT ","marque":"TELEVISION SAMSUNG Smart 65&#039;&#039; SUHD JS9000 3D Curved 4K","source":"Mytek"},{"tv":"T&eacute;l&eacute;viseurs T&eacute;l&eacute;viseur HD SABA 32&quot;","lien":"http:\/\/www.tunisianet.com.tn\/vente-tv-samsung-led-tunisie\/13536-televiseur-televiseur-hd-saba-32.html","photo":"http:\/\/www.tunisianet.com.tn\/38330-home\/televiseur-televiseur-hd-saba-32.jpg","prix":"485,000 DT","pouces":33,"marque":"SABA","source":"TunisiaNet"},{"tv":"T&eacute;l&eacute;viseurs T&eacute;l&eacute;viseur TCL HD 32&quot; \/ 32D2700","lien":"http:\/\/www.tunisianet.com.tn\/vente-tv-samsung-led-tunisie\/12823-televiseur-tcl-hd-32-32b2810.html","photo":"http:\/\/www.tunisianet.com.tn\/36368-home\/televiseur-tcl-hd-32-32b2810.jpg","prix":"609,000 DT","pouces":32,"marque":"TCL","source":"TunisiaNet"},{"tv":"T&eacute;l&eacute;viseurs T&eacute;l&eacute;viseur LG 32&quot; IPS LED HD 32LB551B","lien":"http:\/\/www.tunisianet.com.tn\/vente-tv-samsung-led-tunisie\/13275-televiseur-lg-32-ips-led-hd-32lb551b.html","photo":"http:\/\/www.tunisianet.com.tn\/37600-home\/televiseur-lg-32-ips-led-hd-32lb551b.jpg","prix":"699,000 DT","pouces":28,"marque":"LG","source":"TunisiaNet"},{"tv":"T&eacute;l&eacute;viseurs T&eacute;l&eacute;viseur  LED HD Samsung 32 pouces S&eacute;rie 4","lien":"http:\/\/www.tunisianet.com.tn\/vente-tv-samsung-led-tunisie\/10269-televiseur-led-hd-samsung-32-pouces-serie-4.html","photo":"http:\/\/www.tunisianet.com.tn\/29554-home\/televiseur-led-hd-samsung-32-pouces-serie-4.jpg","prix":"699,000 DT","pouces":41,"marque":"Samsung","source":"TunisiaNet"},{"tv":"T&eacute;l&eacute;viseurs T&eacute;l&eacute;viseur Sony Bravia LED HD 32&quot; S&eacute;rie R420B","lien":"http:\/\/www.tunisianet.com.tn\/vente-tv-samsung-led-tunisie\/9331-televiseur-sony-bravia-led-full-hd-46-serie-r450a.html","photo":"http:\/\/www.tunisianet.com.tn\/26460-home\/televiseur-sony-bravia-led-full-hd-46-serie-r450a.jpg","prix":"699,000 DT","pouces":44,"marque":"Sony","source":"TunisiaNet"},{"tv":"T&eacute;l&eacute;viseurs T&eacute;l&eacute;viseur Full HD SABA 40&quot;","lien":"http:\/\/www.tunisianet.com.tn\/vente-tv-samsung-led-tunisie\/15509-televiseur-full-hd-saba-40.html","photo":"http:\/\/www.tunisianet.com.tn\/43885-home\/televiseur-full-hd-saba-40.jpg","prix":"769,000 DT","pouces":38,"marque":"SABA","source":"TunisiaNet"},{"tv":"T&eacute;l&eacute;viseurs T&eacute;l&eacute;viseur TCL Full HD 40&quot; \/ 40B2810","lien":"http:\/\/www.tunisianet.com.tn\/vente-tv-samsung-led-tunisie\/11803-televiseur-tcl-full-hd-40-40b2810.html","photo":"http:\/\/www.tunisianet.com.tn\/33673-home\/televiseur-tcl-full-hd-40-40b2810.jpg","prix":"929,000 DT","pouces":37,"marque":"TCL","source":"TunisiaNet"},{"tv":"T&eacute;l&eacute;viseurs T&eacute;l&eacute;viseur Full HD SABA 48&quot;","lien":"http:\/\/www.tunisianet.com.tn\/vente-tv-samsung-led-tunisie\/15511-televiseur-full-hd-saba-48.html","photo":"http:\/\/www.tunisianet.com.tn\/43887-home\/televiseur-full-hd-saba-48.jpg","prix":"1 149,000 DT","pouces":38,"marque":"SABA","source":"TunisiaNet"},{"tv":"T&eacute;l&eacute;viseurs T&eacute;l&eacute;viseur LG 43&quot; LED Full HD 43LF5100","lien":"http:\/\/www.tunisianet.com.tn\/vente-tv-samsung-led-tunisie\/15638-televiseur-lg-43-led-full-hd-43lf5100.html","photo":"http:\/\/www.tunisianet.com.tn\/44209-home\/televiseur-lg-43-led-full-hd-43lf5100.jpg","prix":"1 215,000 DT","pouces":28,"marque":"LG","source":"TunisiaNet"},{"tv":"T&eacute;l&eacute;viseurs T&eacute;l&eacute;viseur Sony Bravia LED Full HD 40&quot; S&eacute;rie R470B","lien":"http:\/\/www.tunisianet.com.tn\/vente-tv-samsung-led-tunisie\/9340-televiseur-sony-bravia-led-full-hd-40-serie-r470b.html","photo":"http:\/\/www.tunisianet.com.tn\/26496-home\/televiseur-sony-bravia-led-full-hd-40-serie-r470b.jpg","prix":"1 239,000 DT","pouces":49,"marque":"Sony","source":"TunisiaNet"},{"tv":"T&eacute;l&eacute;viseurs T&eacute;l&eacute;viseur LED Full HD Samsung 40 pouces S&eacute;rie 5","lien":"http:\/\/www.tunisianet.com.tn\/vente-tv-samsung-led-tunisie\/15791-televiseur-led-full-hd-samsung-40-pouces-serie-5.html","photo":"http:\/\/www.tunisianet.com.tn\/44727-home\/televiseur-led-full-hd-samsung-40-pouces-serie-5.jpg","prix":"1 249,000 DT","pouces":45,"marque":"Samsung","source":"TunisiaNet"},{"tv":"T&eacute;l&eacute;viseurs T&eacute;l&eacute;viseur Sony Bravia LED Full HD 40&quot; S&eacute;rie W600","lien":"http:\/\/www.tunisianet.com.tn\/vente-tv-samsung-led-tunisie\/9341-televiseur-sony-bravia-led-full-hd-40-serie-w600.html","photo":"http:\/\/www.tunisianet.com.tn\/26499-home\/televiseur-sony-bravia-led-full-hd-40-serie-w600.jpg","prix":"1 539,000 DT","pouces":49,"marque":"Sony","source":"TunisiaNet"},{"tv":"T&eacute;l&eacute;viseurs T&eacute;l&eacute;viseur LG 49&quot; LED Full HD 49LF5400","lien":"http:\/\/www.tunisianet.com.tn\/vente-tv-samsung-led-tunisie\/15639-televiseur-lg-49-led-full-hd-49lf5400.html","photo":"http:\/\/www.tunisianet.com.tn\/44219-home\/televiseur-lg-49-led-full-hd-49lf5400.jpg","prix":"1 545,000 DT","pouces":28,"marque":"LG","source":"TunisiaNet"},{"tv":"T&eacute;l&eacute;viseurs T&eacute;l&eacute;viseur Samsung 55&quot; LED UHD 4K 140 cm Smart TV","lien":"http:\/\/www.tunisianet.com.tn\/vente-tv-samsung-led-tunisie\/13794-televiseur-samsung-55-led-uhd-4k-140-cm-smart-tv.html","photo":"http:\/\/www.tunisianet.com.tn\/39013-home\/televiseur-samsung-55-led-uhd-4k-140-cm-smart-tv.jpg","prix":"4 229,000 DT","pouces":33,"marque":"Samsung","source":"TunisiaNet"},{"tv":"T&eacute;l&eacute;viseurs T&eacute;l&eacute;viseur LG ULTRA HD Smart 49&quot;","lien":"http:\/\/www.tunisianet.com.tn\/vente-tv-samsung-led-tunisie\/13755-televiseur-lg-ultra-hd-smart-49.html","photo":"http:\/\/www.tunisianet.com.tn\/38858-home\/televiseur-lg-ultra-hd-smart-49.jpg","prix":"4 653,000 DT","pouces":43,"marque":"LG","source":"TunisiaNet"},{"tv":"T&eacute;l&eacute;viseurs T&eacute;l&eacute;viseur LG ULTRA HD Smart 55&quot;","lien":"http:\/\/www.tunisianet.com.tn\/vente-tv-samsung-led-tunisie\/13758-televiseur-lg-ultra-hd-smart-55.html","photo":"http:\/\/www.tunisianet.com.tn\/38863-home\/televiseur-lg-ultra-hd-smart-55.jpg","prix":"6 425,000 DT","pouces":43,"marque":"LG","source":"TunisiaNet"},{"tv":"T&eacute;l&eacute;viseurs T&eacute;l&eacute;viseur LG ULTRA HD Smart 60&quot;","lien":"http:\/\/www.tunisianet.com.tn\/vente-tv-samsung-led-tunisie\/13759-televiseur-lg-ultra-hd-smart-60.html","photo":"http:\/\/www.tunisianet.com.tn\/38868-home\/televiseur-lg-ultra-hd-smart-60.jpg","prix":"8 199,000 DT","pouces":43,"marque":"LG","source":"TunisiaNet"}]